{
    "result": 0,
    "data": [
      {
        "key": 1,
        "strDailyUnitPriceText": "null당 56원",
        "cardObj": {},
        "strGModelCnt": "1",
        "strMainIngred": "MSM",
        "strCardPrice": "",
        "strFncRankNm": "",
        "strCateCd": "15010101",
        "strMainCom": "MSM, 비타민D",
        "strDecreaseRate": "5",
        "strModelName": "필리서치 관절 연골엔 옵티머스트 673mg 90정 [1개]",
        "strCardName": "",
        "totalCpy": 60000,
        "strMinPrice": "33,600",
        "strBbsNum": "1,385",
        "intSaleCnt": 109,
        "strReviewKeyword": "",
        "strSpecTag": "health",
        "strBbsPoint": "4.6",
        "strCondiName": "1개",
        "strSpec1": "MSM 2000mg",
        "strSpec2": "1개월분 1개",
        "strSpec3": "1일 1회, 3정",
        "strMainFnc": "관절,뼈건강, 칼슘흡수, 면역력",
        "strDailyPrice": "1,120",
        "arrAiReviewKeyword": [
          {
            "view_kwd": "효과",
            "sumry_cts": "몇년을 고생한 다리통증을 옵티머스로 해결"
          },
          {
            "view_kwd": "제품",
            "sumry_cts": "리뉴얼된 제품을 보내주셨어요"
          },
          {
            "view_kwd": "가성비",
            "sumry_cts": "가격 대비 효과가 좋았어요"
          }
        ],
        "arrReview": [
          {
            "contents": "가격도 착하고 배송도 빠르고 안전하게 잘 도착하였습니다.\n무릎관절이 아파서 먹고있는데 안먹을때 보다는 통증이 조금 덜한것 같아 계속 구입하고 있습니다.\n무릎이 낳지는 않겠지만 꾸준히 먹어보겠습니다,\n감사합니다.",
            "title": "가격도 착하고 배송도 빠르고 안전하게 잘 도착하였습니다...",
            "point": "5"
          }
        ],
        "strModelNo": "101872697",
        "strMainIngredAmount": "2000.0mg",
        "totalUnit": "mg",
        "strImageUrl": "https://image.enuri.info/webimage_300/17205900000/17205960000/17205961899",
        "strWowPrice": ""
      },
      {
        "key": 2,
        "strDailyUnitPriceText": "null당 139원",
        "cardObj": {},
        "strGModelCnt": "1",
        "strMainIngred": "비타민C",
        "strCardPrice": "",
        "strFncRankNm": "",
        "strCateCd": "15010202",
        "strMainCom": "비타민C, 비타민D, 비오틴 외 1개",
        "strDecreaseRate": "2",
        "strModelName": "고려은단 비타민C 골드 플러스 240정 [1개]",
        "strCardName": "",
        "totalCpy": 240000,
        "strMinPrice": "33,460",
        "strBbsNum": "10,001",
        "intSaleCnt": 66,
        "strReviewKeyword": "",
        "strSpecTag": "health",
        "strBbsPoint": "4.8",
        "strCondiName": "1개",
        "strSpec1": "비타민C 1000mg",
        "strSpec2": "8개월분 1개",
        "strSpec3": "1일 1회, 1정",
        "strMainFnc": "면역력, 관절,뼈건강, 피부건강 외 3개",
        "strDailyPrice": "139",
        "arrAiReviewKeyword": [
          {
            "view_kwd": "효과",
            "sumry_cts": "효과는 개인차가 있지만, 믿고 먹는 제품"
          },
          {
            "view_kwd": "배송",
            "sumry_cts": "빠른배송으로 만족"
          },
          {
            "view_kwd": "가격",
            "sumry_cts": "여기가 제일 싸네요"
          }
        ],
        "arrReview": [
          {
            "contents": "고려은단 비티민C 품질은 잘 알려져 있습니다. 좋은 제품 만족한 가격에 구매했습니다. 배송도 빠르게 되었습니다.",
            "title": "고려은단 비타민C 골드플러스 240정",
            "point": "5"
          }
        ],
        "strModelNo": "18872424",
        "strMainIngredAmount": "1000.0mg",
        "totalUnit": "mg",
        "strImageUrl": "https://photo3.enuri.info/data/images/service/middle/18872000/18872424.jpg",
        "strWowPrice": ""
      },
      {
        "key": 3,
        "strDailyUnitPriceText": "1mg당 36원",
        "cardObj": {
          "price": "92,790",
          "card_name": "현대스마일카드",
          "card_full_name": "현대스마일카드"
        },
        "strGModelCnt": "1",
        "strMainIngred": "진세노사이드",
        "strCardPrice": "92,790",
        "strFncRankNm": "",
        "strCateCd": "15010528",
        "strMainCom": "",
        "strDecreaseRate": "",
        "strModelName": "믿음의나무 양지 홍삼농축액 068 240g [1개]",
        "strCardName": "현대스마일카드",
        "totalCpy": 2640,
        "strMinPrice": "97,660",
        "strBbsNum": "1,423",
        "intSaleCnt": 4,
        "strReviewKeyword": "",
        "strSpecTag": "health",
        "strBbsPoint": "4.8",
        "strCondiName": "1개",
        "strSpec1": "진세노사이드 33mg",
        "strSpec2": "80일분 1개",
        "strSpec3": "1일 3회, 1g",
        "strMainFnc": "면역력, 항산화, 갱년기",
        "strDailyPrice": "1,220",
        "arrAiReviewKeyword": [
          {
            "view_kwd": "배송",
            "sumry_cts": "빠르고 깔끔한 포장"
          },
          {
            "view_kwd": "가격",
            "sumry_cts": "가성비 좋음, 유명 브랜드보다 저렴함"
          },
          {
            "view_kwd": "가성비",
            "sumry_cts": "성분함량이 높고 효과 좋음, 선물용 가능"
          }
        ],
        "arrReview": [
          {
            "contents": "정말 좋아요. 저렴하고 가성비 있으면서\n배송도 빠르네요..번창하세요",
            "title": "정말 좋아요. 저렴하고 가성비 있으면서",
            "point": "5"
          }
        ],
        "strModelNo": "14076675",
        "strMainIngredAmount": "33.0mg",
        "totalUnit": "mg",
        "strImageUrl": "https://image.enuri.info/webimage_300/8726200000/8726240000/8726249895.jpg",
        "strWowPrice": ""
      },
      {
        "key": 4,
        "strDailyUnitPriceText": "null당 170원",
        "cardObj": {},
        "strGModelCnt": "1",
        "strMainIngred": "비타민C",
        "strCardPrice": "",
        "strFncRankNm": "",
        "strCateCd": "15010202",
        "strMainCom": "비타민C, 비타민D",
        "strDecreaseRate": "",
        "strModelName": "고려은단 비타민C1000 이지+ 비타민D 180정 [1개]",
        "strCardName": "",
        "totalCpy": 90000,
        "strMinPrice": "15,380",
        "strBbsNum": "2,987",
        "intSaleCnt": 0,
        "strReviewKeyword": "",
        "strSpecTag": "health",
        "strBbsPoint": "4.7",
        "strCondiName": "1개",
        "strSpec1": "비타민C 1000mg",
        "strSpec2": "3개월분 1개",
        "strSpec3": "1일 1회, 2정",
        "strMainFnc": "면역력, 관절,뼈건강, 항산화 외 1개",
        "strDailyPrice": "170",
        "arrAiReviewKeyword": [
          {
            "view_kwd": "효과",
            "sumry_cts": "크기가 작아 목넘김 편하고 효과가 좋아요"
          },
          {
            "view_kwd": "배송",
            "sumry_cts": "배송이 빨랐고 포장이 깔끔했어요"
          },
          {
            "view_kwd": "유통기한",
            "sumry_cts": "유통기한이 넉넉해서 좋아요"
          }
        ],
        "arrReview": [
          {
            "contents": "배송 빨라요믿고 구매 했습니다",
            "title": "굿",
            "point": "5"
          }
        ],
        "strModelNo": "66218074",
        "strMainIngredAmount": "1000.0mg",
        "totalUnit": "mg",
        "strImageUrl": "https://photo3.enuri.info/data/images/service/middle/66218000/66218074.jpg",
        "strWowPrice": ""
      },
      {
        "key": 5,
        "strDailyUnitPriceText": "1mg당 317원",
        "cardObj": {},
        "strGModelCnt": "1",
        "strMainIngred": "진세노사이드",
        "strCardPrice": "",
        "strFncRankNm": "",
        "strCateCd": "15010529",
        "strMainCom": "",
        "strDecreaseRate": "10",
        "strModelName": "정관장 홍삼정마일드 센스업 10g 30포 [1개]",
        "strCardName": "",
        "totalCpy": 180,
        "strMinPrice": "57,130",
        "strBbsNum": "1,830",
        "intSaleCnt": 140,
        "strReviewKeyword": "",
        "strSpecTag": "health",
        "strBbsPoint": "4.8",
        "strCondiName": "1개",
        "strSpec1": "진세노사이드 6mg",
        "strSpec2": "1개월분 1개",
        "strSpec3": "1일 1회, 1포",
        "strMainFnc": "면역력, 항산화",
        "strDailyPrice": "1,904",
        "arrAiReviewKeyword": [
          {
            "view_kwd": "배송",
            "sumry_cts": "배송이 빠르고 깔끔하게 도착했어요"
          },
          {
            "view_kwd": "포장",
            "sumry_cts": "깔끔한 포장과 유통기한이 긴 제품이에요"
          },
          {
            "view_kwd": "가격",
            "sumry_cts": "가격이 저렴하고 가성비가 좋아요"
          }
        ],
        "arrReview": [
          {
            "contents": "가격이 계속 올라서 부담이 커지고 있어요.건강생각해서 먹고있는데.....계속 오른다면 다른제품으로 갈아탈듯싶어요.",
            "title": "꾸준히 먹어요",
            "point": "5"
          }
        ],
        "strModelNo": "101623320",
        "strMainIngredAmount": "6.0mg",
        "totalUnit": "mg",
        "strImageUrl": "https://image.enuri.info/webimage_300/13500200000/13500220000/13500223113.jpg",
        "strWowPrice": ""
      },
      {
        "key": 6,
        "strDailyUnitPriceText": "null당 127원",
        "cardObj": {
          "price": "55,040",
          "card_name": "현대스마일카드",
          "card_full_name": "현대스마일카드"
        },
        "strGModelCnt": "1",
        "strMainIngred": "MSM",
        "strCardPrice": "55,040",
        "strFncRankNm": "",
        "strCateCd": "15010101",
        "strMainCom": "MSM, 비타민D",
        "strDecreaseRate": "6",
        "strModelName": "유니시티 조인트 모빌리티 MSM&비타민D 90캡슐 [1개]",
        "strCardName": "현대스마일카드",
        "totalCpy": 45450,
        "strMinPrice": "57,910",
        "strBbsNum": "561",
        "intSaleCnt": 6,
        "strReviewKeyword": "",
        "strSpecTag": "health",
        "strBbsPoint": "4.7",
        "strCondiName": "1개",
        "strSpec1": "MSM 1515mg",
        "strSpec2": "1개월분 1개",
        "strSpec3": "1일 1회, 3캡슐",
        "strMainFnc": "관절,뼈건강, 칼슘흡수, 면역력",
        "strDailyPrice": "1,931",
        "arrAiReviewKeyword": [
          {
            "view_kwd": "효과",
            "sumry_cts": "관절 통증에 탁월한 효과가 있음"
          },
          {
            "view_kwd": "가격",
            "sumry_cts": "가성비 좋고, 계속해서 구매하고 싶은 상품"
          },
          {
            "view_kwd": "재구매",
            "sumry_cts": "7년간 꾸준히 먹는 제품입니다."
          }
        ],
        "arrReview": [
          {
            "contents": "건강하려고 잘~챙겨 먹고 있습니다 맘에 쏙듭니다",
            "title": "조인트 모빌리티",
            "point": "4"
          }
        ],
        "strModelNo": "53500875",
        "strMainIngredAmount": "1515.0mg",
        "totalUnit": "mg",
        "strImageUrl": "https://image.enuri.info/webimage_300/14031700000/14031770000/14031779985",
        "strWowPrice": ""
      },
      {
        "key": 7,
        "strDailyUnitPriceText": "null당 11원",
        "cardObj": {
          "price": "37,830",
          "card_name": "현대스마일카드",
          "card_full_name": "현대스마일카드"
        },
        "strGModelCnt": "1",
        "strMainIngred": "루테인",
        "strCardPrice": "37,830",
        "strFncRankNm": "",
        "strCateCd": "15010122",
        "strMainCom": "루테인, 베타카로틴, 아스타잔틴 외 3개",
        "strDecreaseRate": "1",
        "strModelName": "그랑도눔 루테인 아스타잔틴 지아잔틴 510mg 90캡슐 [2개]",
        "strCardName": "현대스마일카드",
        "totalCpy": 1800,
        "strMinPrice": "40,670",
        "strBbsNum": "2,491",
        "intSaleCnt": 10,
        "strReviewKeyword": "",
        "strSpecTag": "health",
        "strBbsPoint": "4.6",
        "strCondiName": "2개",
        "strSpec1": "루테인 20mg",
        "strSpec2": "3개월분 2개",
        "strSpec3": "1일 1회, 1캡슐",
        "strMainFnc": "눈건강, 항산화, 면역력 외 3개",
        "strDailyPrice": "225",
        "arrAiReviewKeyword": [
          {
            "view_kwd": "효과",
            "sumry_cts": "눈 피로도가 개선되고, 눈 건강에 도움이 됨"
          },
          {
            "view_kwd": "가격",
            "sumry_cts": "가격은 나쁘지 않고, 1+1 이라서 저렴함"
          },
          {
            "view_kwd": "가성비",
            "sumry_cts": "가격도 괜찮고, 효과도 좋아서 가성비가 좋음"
          }
        ],
        "arrReview": [
          {
            "contents": "몇년 먹었는지 기억은 잘 나진 않지만, 돌아가신 어머니와 같이 쭉 복용한 제품입니다",
            "title": "몇년 먹었는지 기억은 잘 나진 않지만, 돌아가신 어머니...",
            "point": "5"
          }
        ],
        "strModelNo": "109796549",
        "strMainIngredAmount": "20.0mg",
        "totalUnit": "mg",
        "strImageUrl": "https://photo3.enuri.info/data/images/service/dnw/master/109796000/109796549.jpg",
        "strWowPrice": ""
      },
      {
        "key": 8,
        "strDailyUnitPriceText": "null당 111원",
        "cardObj": {},
        "strGModelCnt": "1",
        "strMainIngred": "실리마린",
        "strCardPrice": "",
        "strFncRankNm": "",
        "strCateCd": "15010138",
        "strMainCom": "실리마린, 비타민B6, 비타민B1 외 3개",
        "strDecreaseRate": "",
        "strModelName": "GNM자연의품격 건강한 간 밀크씨슬 900mg 30정 [1개]",
        "strCardName": "",
        "totalCpy": 3900,
        "strMinPrice": "3,330",
        "strBbsNum": "87,818",
        "intSaleCnt": 562,
        "strReviewKeyword": "",
        "strSpecTag": "health",
        "strBbsPoint": "4.7",
        "strCondiName": "1개",
        "strSpec1": "실리마린 130mg",
        "strSpec2": "1개월분 1개",
        "strSpec3": "1일 1회, 1정",
        "strMainFnc": "간건강, 단백질 이용, 에너지생산 외 2개",
        "strDailyPrice": "111",
        "arrAiReviewKeyword": [
          {
            "view_kwd": "배송",
            "sumry_cts": "빠르고 편리한 배송"
          },
          {
            "view_kwd": "가격",
            "sumry_cts": "저렴한 가격이라 만족스러워요"
          },
          {
            "view_kwd": "가성비",
            "sumry_cts": "효과가 좋아서 가성비가 좋아요"
          }
        ],
        "arrReview": [
          {
            "contents": "유통기한도 길고 저렴하게 잘 샀습니다. 하루에 먹을 수 있는 영양제를 샀는데 밀크씨슬은 빠져있어서 따로 구매했어요!\n사은품으로 준 구미도 잘 먹겠습니다.",
            "title": "유통기한도 길고 저렴하게 잘 샀습니다. 하루에 먹을 수...",
            "point": "4"
          }
        ],
        "strModelNo": "11593861",
        "strMainIngredAmount": "130.0mg",
        "totalUnit": "mg",
        "strImageUrl": "https://photo3.enuri.info/data/images/service/middle/11593000/11593861.jpg",
        "strWowPrice": ""
      },
      {
        "key": 9,
        "strDailyUnitPriceText": "null당 265원",
        "cardObj": {},
        "strGModelCnt": "1",
        "strMainIngred": "프로바이오틱스",
        "strCardPrice": "",
        "strFncRankNm": "",
        "strCateCd": "15010307",
        "strMainCom": "",
        "strDecreaseRate": "",
        "strModelName": "뉴팜 락토리움 프로바이오틱스 키즈 앤 베이비 생유산균 2g 50포 [1개]",
        "strCardName": "",
        "totalCpy": 400,
        "strMinPrice": "10,620",
        "strBbsNum": "1,315",
        "intSaleCnt": 0,
        "strReviewKeyword": "",
        "strSpecTag": "health",
        "strBbsPoint": "4.7",
        "strCondiName": "1개",
        "strSpec1": "프로바이오틱스 8억 CFU",
        "strSpec2": "50일분 1개",
        "strSpec3": "1일 1회, 1포",
        "strMainFnc": "",
        "strDailyPrice": "212",
        "arrAiReviewKeyword": [
          {
            "view_kwd": "효과",
            "sumry_cts": "아이들 방귀 냄새가 사라졌고 쾌변해요"
          },
          {
            "view_kwd": "복용",
            "sumry_cts": "향도 맛도 강하지 않은 무난한 맛이에요"
          },
          {
            "view_kwd": "배송",
            "sumry_cts": "스마일배송이 가장 빠르고 저렴해요"
          }
        ],
        "arrReview": [
          {
            "contents": "우리아기에게 잘 먹이고있어요^^아이도 좋아해요^^서비스 루테인 잘먹겠습니다？？",
            "title": "계속 잘 먹이고있어요~",
            "point": "5"
          }
        ],
        "strModelNo": "19756635",
        "strMainIngredAmount": "8.0억 CFU",
        "totalUnit": "억 CFU",
        "strImageUrl": "https://image.enuri.info/webimage_300/7582500000/7582570000/7582570206.jpg",
        "strWowPrice": ""
      },
      {
        "key": 10,
        "strDailyUnitPriceText": "null당 35원",
        "cardObj": {},
        "strGModelCnt": "1",
        "strMainIngred": "EPA+DHA",
        "strCardPrice": "",
        "strFncRankNm": "",
        "strCateCd": "15010111",
        "strMainCom": "EPA+DHA, 비타민D, 비타민E",
        "strDecreaseRate": "",
        "strModelName": "닥터린 초임계 알티지 오메가3 1025mg 30캡슐 [1개]",
        "strCardName": "",
        "totalCpy": 18000,
        "strMinPrice": "6,350",
        "strBbsNum": "39,662",
        "intSaleCnt": 240,
        "strReviewKeyword": "",
        "strSpecTag": "health",
        "strBbsPoint": "4.8",
        "strCondiName": "1개",
        "strSpec1": "EPA+DHA 600mg",
        "strSpec2": "1개월분 1개",
        "strSpec3": "1일 1회, 1캡슐",
        "strMainFnc": "혈행개선, 관절,뼈건강, 항산화 외 3개",
        "strDailyPrice": "211",
        "arrAiReviewKeyword": [
          {
            "view_kwd": "효과",
            "sumry_cts": "고지혈증에 효과적, 메스꺼움 및 냄새 없음"
          },
          {
            "view_kwd": "배송",
            "sumry_cts": "빠른 배송에 감사"
          },
          {
            "view_kwd": "가성비",
            "sumry_cts": "저렴한 가격, 가성비 '갑'인 제품"
          }
        ],
        "arrReview": [
          {
            "contents": "알이 커서 걱정했는데 ㅋㅅ**는 좀 딱딱했는데 목넘김 좋네요. 딸아이도 한번 먹어보라하니 괜찮다 하네요. 말랑말랑해서 그런가봐요. 그리고 낱개로 포장되어 좋아요",
            "title": "알이 커서 걱정했는데 ㅋㅅ**는 좀 딱딱했는데 목넘김 ...",
            "point": "5"
          }
        ],
        "strModelNo": "66850493",
        "strMainIngredAmount": "600.0mg",
        "totalUnit": "mg",
        "strImageUrl": "https://photo3.enuri.info/data/images/service/middle/66850000/66850493.jpg",
        "strWowPrice": ""
      },
      {
        "key": 11,
        "strDailyUnitPriceText": "null당 220원",
        "cardObj": {},
        "strGModelCnt": "1",
        "strMainIngred": "칼슘",
        "strCardPrice": "",
        "strFncRankNm": "",
        "strCateCd": "15010203",
        "strMainCom": "",
        "strDecreaseRate": "",
        "strModelName": "NNP 꾸미바이트 꾸미베어스 칼슘+비타민D 60구미 [1개]",
        "strCardName": "",
        "totalCpy": 6600,
        "strMinPrice": "14,550",
        "strBbsNum": "1,845",
        "intSaleCnt": 0,
        "strReviewKeyword": "",
        "strSpecTag": "health",
        "strBbsPoint": "4.8",
        "strCondiName": "1개",
        "strSpec1": "칼슘 220mg",
        "strSpec2": "1개월분 1개",
        "strSpec3": "1일 1회, 2구미",
        "strMainFnc": "",
        "strDailyPrice": "485",
        "arrAiReviewKeyword": [
          {
            "view_kwd": "효과",
            "sumry_cts": "아이들이 잘 먹어요"
          },
          {
            "view_kwd": "배송",
            "sumry_cts": "빠르고 좋아요"
          },
          {
            "view_kwd": "가성비",
            "sumry_cts": "맛, 가격 다 맘에 들어요"
          }
        ],
        "arrReview": [
          {
            "contents": "맛있어요. 젤리맛~ 치아에는 안좋을 것 같은데..\n칼슘, 비타민디 영양제 맛이 있으니 ^^",
            "title": "맛있어요. 젤리맛~ 치아에는 안좋을",
            "point": "5"
          }
        ],
        "strModelNo": "10565585",
        "strMainIngredAmount": "220.0mg",
        "totalUnit": "mg",
        "strImageUrl": "https://photo3.enuri.info/data/images/service/middle/10565000/10565585.jpg",
        "strWowPrice": ""
      },
      {
        "key": 12,
        "strDailyUnitPriceText": "null당 127원",
        "cardObj": {},
        "strGModelCnt": "1",
        "strMainIngred": "실리마린",
        "strCardPrice": "",
        "strFncRankNm": "",
        "strCateCd": "15010138",
        "strMainCom": "실리마린, 엽산, 아연 외 6개",
        "strDecreaseRate": "",
        "strModelName": "한미양행 간에는 밀크씨슬 900mg 90정 [1개]",
        "strCardName": "",
        "totalCpy": 11700,
        "strMinPrice": "11,500",
        "strBbsNum": "614",
        "intSaleCnt": 12,
        "strReviewKeyword": "",
        "strSpecTag": "health",
        "strBbsPoint": "4.8",
        "strCondiName": "1개",
        "strSpec1": "실리마린 130mg",
        "strSpec2": "3개월분 1개",
        "strSpec3": "1일 1회, 1정",
        "strMainFnc": "간건강, 영양보충, 면역력 외 7개",
        "strDailyPrice": "127",
        "arrAiReviewKeyword": [
          {
            "view_kwd": "효과",
            "sumry_cts": "피로회복용으로 구매했는데 효과가 좋아요"
          },
          {
            "view_kwd": "함량",
            "sumry_cts": "높은함량으로 하루 1번이면 돼서 좋아요"
          },
          {
            "view_kwd": "가성비",
            "sumry_cts": "가성비 좋은 제품, 저렴한 가격으로 만족함"
          }
        ],
        "arrReview": [
          {
            "contents": "빠른배송 감사합니다 재구매할께요",
            "title": "빠른배송 감사합니다 재구매할께요",
            "point": "5"
          }
        ],
        "strModelNo": "73437840",
        "strMainIngredAmount": "130.0mg",
        "totalUnit": "mg",
        "strImageUrl": "https://image.enuri.info/webimage_300/13621800000/13621860000/13621864346",
        "strWowPrice": ""
      },
      {
        "key": 13,
        "strDailyUnitPriceText": "null당 11원",
        "cardObj": {},
        "strGModelCnt": "1",
        "strMainIngred": "루테인",
        "strCardPrice": "",
        "strFncRankNm": "",
        "strCateCd": "15010122",
        "strMainCom": "루테인, 지아잔틴, 비타민A 외 5개",
        "strDecreaseRate": "",
        "strModelName": "뉴트리원 루테인 지아잔틴 164 500mg 30캡슐 [1개]",
        "strCardName": "",
        "totalCpy": 480,
        "strMinPrice": "5,490",
        "strBbsNum": "19,425",
        "intSaleCnt": 398,
        "strReviewKeyword": "",
        "strSpecTag": "health",
        "strBbsPoint": "4.7",
        "strCondiName": "1개",
        "strSpec1": "루테인 16mg",
        "strSpec2": "1개월분 1개",
        "strSpec3": "1일 1회, 1캡슐",
        "strMainFnc": "눈건강, 황반변성예방, 항산화 외 3개",
        "strDailyPrice": "183",
        "arrAiReviewKeyword": [
          {
            "view_kwd": "함량",
            "sumry_cts": "뉴트리원은 함량이 높아 믿고 구매했어요"
          },
          {
            "view_kwd": "효과",
            "sumry_cts": "눈건강에 도움되는 루테인과 지아잔틴 함유"
          },
          {
            "view_kwd": "가성비",
            "sumry_cts": "가격 대비 품질이 좋은 제품"
          }
        ],
        "arrReview": [
          {
            "contents": "늘 먹는 제품으로 유통기한도 넉넉하여 재구매 의사 있습니다.",
            "title": "늘 먹는 제품으로 유통기한도 넉넉하여 재구매 의사 있습...",
            "point": "4"
          }
        ],
        "strModelNo": "33056991",
        "strMainIngredAmount": "16.0mg",
        "totalUnit": "mg",
        "strImageUrl": "https://photo3.enuri.info/data/images/service/middle/33056000/33056991.jpg",
        "strWowPrice": ""
      },
      {
        "key": 14,
        "strDailyUnitPriceText": "null당 216원",
        "cardObj": {},
        "strGModelCnt": "1",
        "strMainIngred": "칼슘",
        "strCardPrice": "",
        "strFncRankNm": "",
        "strCateCd": "15010203",
        "strMainCom": "",
        "strDecreaseRate": "",
        "strModelName": "노바렉스 쁘띠 앤 칼마디 60정 [1개]",
        "strCardName": "",
        "totalCpy": 12000,
        "strMinPrice": "25,970",
        "strBbsNum": "4,715",
        "intSaleCnt": 1,
        "strReviewKeyword": "",
        "strSpecTag": "health",
        "strBbsPoint": "4.8",
        "strCondiName": "1개",
        "strSpec1": "칼슘 400mg",
        "strSpec2": "1개월분 1개",
        "strSpec3": "1일 1회, 2정",
        "strMainFnc": "",
        "strDailyPrice": "865",
        "arrAiReviewKeyword": [
          {
            "view_kwd": "효과",
            "sumry_cts": "무릎통증 완화, 칼슘과 비타민D 섭취에 좋음"
          },
          {
            "view_kwd": "배송",
            "sumry_cts": "빠르고 안전한 배송"
          },
          {
            "view_kwd": "가격",
            "sumry_cts": "적당한 가격, 저렴한 가격으로 구입"
          }
        ],
        "arrReview": [
          {
            "contents": "배송 빠르고 상품 좋습니다",
            "title": "배송 빠르고 상품 좋습니다",
            "point": "4"
          }
        ],
        "strModelNo": "16433701",
        "strMainIngredAmount": "400.0mg",
        "totalUnit": "mg",
        "strImageUrl": "https://image.enuri.info/webimage_300/14066800000/14066820000/14066820616",
        "strWowPrice": ""
      },
      {
        "key": 15,
        "strDailyUnitPriceText": "null당 117원",
        "cardObj": {},
        "strGModelCnt": "1",
        "strMainIngred": "프로바이오틱스",
        "strCardPrice": "",
        "strFncRankNm": "",
        "strCateCd": "15010307",
        "strMainCom": "",
        "strDecreaseRate": "11",
        "strModelName": "세노비스 키즈 수퍼바이오틱스 딸기 1g 30포 [1개]",
        "strCardName": "",
        "totalCpy": 1500,
        "strMinPrice": "17,380",
        "strBbsNum": "2,629",
        "intSaleCnt": 4,
        "strReviewKeyword": "",
        "strSpecTag": "health",
        "strBbsPoint": "4.8",
        "strCondiName": "1개",
        "strSpec1": "프로바이오틱스 50억 CFU",
        "strSpec2": "1개월분 1개",
        "strSpec3": "1일 1회, 1포",
        "strMainFnc": "",
        "strDailyPrice": "589",
        "arrAiReviewKeyword": [
          {
            "view_kwd": "효과",
            "sumry_cts": "변비 개선, 방구 감소, 화장실 잘가게 돼요"
          },
          {
            "view_kwd": "포장",
            "sumry_cts": "뽁뽁이 포장으로 안전하게 배송됐어요"
          },
          {
            "view_kwd": "가격",
            "sumry_cts": "쿠폰할인으로 저렴하게 구매했어요"
          }
        ],
        "arrReview": [
          {
            "contents": "아이 영양제를 잘 챙기는 편인데 이번에 세노비스 어린이 유산균 가격이 괜찮고 사은품도 줘서 구매했어요 어렸을때 먹었던거라 맛은 예상했었고 50억 유산균이고 실온보관이라 가지고 다닐때도 안심되요 다만!!!  뜯어먹는 부분이 손으로 불가해서 불편합니다ㅠ가위를 들고다닐수도 없고\n혼자 뜯어먹는 아이의 경우에도 개봉이 어려워서 자꾸 엄마찾네요ㅠㅠ14세까지 복용가능인데 유산균포장용지를 바꾸는게 좋을듯해요",
            "title": "아이 영양제를 잘 챙기는 편인데 이번에 세노비스 어린이",
            "point": "5"
          }
        ],
        "strModelNo": "24000208",
        "strMainIngredAmount": "50.0억 CFU",
        "totalUnit": "억 CFU",
        "strImageUrl": "https://photo3.enuri.info/data/images/service/middle/24000000/24000208.jpg",
        "strWowPrice": ""
      }
    ]
  }